LogAppRestClientLibrary/Environment.py
LogAppRestClientLibrary/__init__.py
LogAppRestClientLibrary/Endpoints/Alert.py
LogAppRestClientLibrary/Endpoints/AlertRule.py
LogAppRestClientLibrary/Endpoints/ConfigurationGroup.py
LogAppRestClientLibrary/Endpoints/LogAgent.py
LogAppRestClientLibrary/Endpoints/__init__.py
LogAppRestClientLibrary/RequestHandlers/IRequestHandler.py
LogAppRestClientLibrary/RequestHandlers/Real_request.py
LogAppRestClientLibrary/RequestHandlers/__init__.py
LogAppClientLibrary-0.1.9.dist-info/METADATA
LogAppClientLibrary-0.1.9.dist-info/WHEEL
LogAppClientLibrary-0.1.9.dist-info/top_level.txt
LogAppClientLibrary-0.1.9.dist-info/RECORD
