Metadata-Version: 2.1
Name: LogAppClientLibrary
Version: 0.1.9
Summary: Client Library für LogApp von iqsol
Home-page: UNKNOWN
Author: Hannes Scheibelauer
Author-email: your@email.com
License: UNKNOWN
Platform: UNKNOWN
